luma_ai_mcp_server/__init__.py
luma_ai_mcp_server/__main__.py
luma_ai_mcp_server/server.py
mseep_luma_ai_mcp_server-0.1.2.dist-info/METADATA
mseep_luma_ai_mcp_server-0.1.2.dist-info/WHEEL
mseep_luma_ai_mcp_server-0.1.2.dist-info/entry_points.txt
mseep_luma_ai_mcp_server-0.1.2.dist-info/RECORD
