Metadata-Version: 2.4
Name: mseep-luma-ai-mcp-server
Version: 0.1.2
Summary: MCP server for Luma AI video generation
Author-email: mseep <support@skydeck.ai>
Maintainer-email: mseep <support@skydeck.ai>
Requires-Python: >=3.10
Requires-Dist: click>=8.1.0
Requires-Dist: httpx>=0.24.0
Requires-Dist: mcp>=0.2.0
Requires-Dist: pydantic>=2.0.0
Requires-Dist: python-dotenv>=1.0.0
Provides-Extra: test
Requires-Dist: pytest-asyncio>=0.21.0; extra == 'test'
Requires-Dist: pytest-cov>=4.1.0; extra == 'test'
Requires-Dist: pytest>=7.0.0; extra == 'test'
